mcdfpy/__init__.py
mcdfpy/blocks.py
mcdfpy/recodeitemapi.py
mcdfpy/template.py
mcdfpy/variables.py
McDFPy-1.0.0.dist-info/LICENSE
McDFPy-1.0.0.dist-info/METADATA
McDFPy-1.0.0.dist-info/WHEEL
McDFPy-1.0.0.dist-info/top_level.txt
McDFPy-1.0.0.dist-info/RECORD
