Metadata-Version: 2.1
Name: McDFPy
Version: 1.0.0
Summary: A python library to create code for the Minecraft server DiamondFire (https://mcdiamondfire.com).
Home-page: https://github.com/AlignedCookie88/McDFPy
Author: AlignedCookie88
Author-email: AlignedCookie88 <contact@alignedcookie88.com>
License: MIT License
Project-URL: Homepage, https://github.com/AlignedCookie88/McDFPy
Project-URL: Bug Reports, https://github.com/AlignedCookie88/McDFPy/issues
Project-URL: Source, https://github.com/AlignedCookie88/McDFPy/
Keywords: minecraft,diamondfire,development
Requires-Python: >=3.7, <4
License-File: LICENSE
